LICENSE
MANIFEST.in
README.rst
VERSION
setup.py
elasticsearch_opentracing/__init__.py
elasticsearch_opentracing.egg-info/PKG-INFO
elasticsearch_opentracing.egg-info/SOURCES.txt
elasticsearch_opentracing.egg-info/dependency_links.txt
elasticsearch_opentracing.egg-info/requires.txt
elasticsearch_opentracing.egg-info/top_level.txt