Metadata-Version: 1.1
Name: elasticsearch-opentracing
Version: 0.1.4
Summary: OpenTracing support for Elasticsearch
Home-page: https://github.com/opentracing-contrib/python-elasticsearch/
Author: Carlos Alberto Cortez
Author-email: calberto.cortez@gmail.com
License: Apache License 2.0
Download-URL: https://github.com/opentracing-contrib/python-elasticsearch/tarball/0.1.4
Platform: any
Classifier: Intended Audience :: Developers
Classifier: License :: OSI Approved :: BSD License
Classifier: Operating System :: OS Independent
Classifier: Programming Language :: Python
Classifier: Topic :: Software Development :: Libraries :: Python Modules
